jakym/__init__.py
jakym/__main__.py
jakym/downloader.py
jakym/player.py
jakym/playlistmanager.py
jakym-0.4.1.dist-info/LICENSE
jakym-0.4.1.dist-info/METADATA
jakym-0.4.1.dist-info/WHEEL
jakym-0.4.1.dist-info/entry_points.txt
jakym-0.4.1.dist-info/top_level.txt
jakym-0.4.1.dist-info/RECORD
