Metadata-Version: 2.1
Name: jakym
Version: 0.4.1
Summary: Just Another Konsole YouTube-Music
Home-page: https://github.com/themayankjha/JAKYM
Author: Mayank Jha
Author-email: jhamayank159@gmail.com
Classifier: Programming Language :: Python :: 3
Classifier: License :: OSI Approved :: GNU General Public License v3 (GPLv3)
Classifier: Operating System :: OS Independent
License-File: LICENSE
Requires-Dist: yt-dlp
Requires-Dist: pyfiglet
Requires-Dist: requests
Requires-Dist: pydub
Requires-Dist: termcolor
Requires-Dist: beautifulsoup4
Requires-Dist: colorama
Requires-Dist: lxml
